odoo/addons/fetchmail_attach_from_folder/README.rst
odoo/addons/fetchmail_attach_from_folder/__init__.py
odoo/addons/fetchmail_attach_from_folder/__manifest__.py
odoo/addons/fetchmail_attach_from_folder/i18n/de.po
odoo/addons/fetchmail_attach_from_folder/i18n/es.po
odoo/addons/fetchmail_attach_from_folder/i18n/fetchmail_attach_from_folder.pot
odoo/addons/fetchmail_attach_from_folder/i18n/fr.po
odoo/addons/fetchmail_attach_from_folder/i18n/fr_CA.po
odoo/addons/fetchmail_attach_from_folder/i18n/it.po
odoo/addons/fetchmail_attach_from_folder/i18n/pt_BR.po
odoo/addons/fetchmail_attach_from_folder/i18n/ru.po
odoo/addons/fetchmail_attach_from_folder/i18n/sl.po
odoo/addons/fetchmail_attach_from_folder/match_algorithm/__init__.py
odoo/addons/fetchmail_attach_from_folder/match_algorithm/email_domain.py
odoo/addons/fetchmail_attach_from_folder/match_algorithm/email_exact.py
odoo/addons/fetchmail_attach_from_folder/models/__init__.py
odoo/addons/fetchmail_attach_from_folder/models/fetchmail_server.py
odoo/addons/fetchmail_attach_from_folder/models/fetchmail_server_folder.py
odoo/addons/fetchmail_attach_from_folder/readme/CONFIGURE.md
odoo/addons/fetchmail_attach_from_folder/readme/CONTRIBUTORS.md
odoo/addons/fetchmail_attach_from_folder/readme/DESCRIPTION.md
odoo/addons/fetchmail_attach_from_folder/readme/USAGE.md
odoo/addons/fetchmail_attach_from_folder/security/ir.model.access.csv
odoo/addons/fetchmail_attach_from_folder/static/description/icon.png
odoo/addons/fetchmail_attach_from_folder/static/description/index.html
odoo/addons/fetchmail_attach_from_folder/tests/__init__.py
odoo/addons/fetchmail_attach_from_folder/tests/test_match_algorithms.py
odoo/addons/fetchmail_attach_from_folder/views/fetchmail_server.xml
odoo/addons/fetchmail_attach_from_folder/wizard/__init__.py
odoo/addons/fetchmail_attach_from_folder/wizard/attach_mail_manually.py
odoo/addons/fetchmail_attach_from_folder/wizard/attach_mail_manually.xml
odoo_addon_fetchmail_attach_from_folder-18.0.1.1.0.2.dist-info/METADATA
odoo_addon_fetchmail_attach_from_folder-18.0.1.1.0.2.dist-info/WHEEL
odoo_addon_fetchmail_attach_from_folder-18.0.1.1.0.2.dist-info/top_level.txt
odoo_addon_fetchmail_attach_from_folder-18.0.1.1.0.2.dist-info/RECORD
