Metadata-Version: 2.1
Name: odoo-addon-fetchmail_attach_from_folder
Version: 18.0.1.1.0.2
Requires-Python: >=3.10
Requires-Dist: odoo==18.0.*
Summary: Attach mails in an IMAP folder to existing objects
Home-page: https://github.com/OCA/server-tools
License: AGPL-3
Author: Therp BV,Odoo Community Association (OCA)
Author-email: support@odoo-community.org
Classifier: Programming Language :: Python
Classifier: Framework :: Odoo
Classifier: Framework :: Odoo :: 18.0
Classifier: License :: OSI Approved :: GNU Affero General Public License v3
